{
  "facetId": "emotional_permeability",
  "version": "1.0",
  "questionSet": "OCTET_8",
  "questions": [
    {
      "question_id": "ep_core_1",
      "text": {
        "zh": "當處於眾人嘈雜之地，您是否常覺自身氣場如籬落破損，外人之喜怒哀樂易趁虛而入？",
        "en": "In noisy crowds, do you feel your aura is like a broken fence, allowing others' emotions to easily intrude?"
      },
      "type": "core_state",
      "options": [
        {
          "value": 0,
          "label": {
            "zh": "氣場穩固",
            "en": "Solid aura"
          }
        },
        {
          "value": 2,
          "label": {
            "zh": "偶有滲入",
            "en": "Occasionally intrudes"
          }
        },
        {
          "value": 4,
          "label": {
            "zh": "極易受侵",
            "en": "Easily invaded"
          }
        }
      ],
      "scoring": {
        "direction": "higher_is_worse",
        "weight": 1.5
      }
    },
    {
      "question_id": "ep_core_2",
      "text": {
        "zh": "與情緒激動者共處後，您是否感覺身上沾染了對方的「氣」，久久難以散去？",
        "en": "After being with emotional people, do you feel stained by their 'Qi', unable to disperse it?"
      },
      "type": "core_state",
      "options": [
        {
          "value": 0,
          "label": {
            "zh": "過水無痕",
            "en": "Water over stone"
          }
        },
        {
          "value": 2,
          "label": {
            "zh": "需時淨化",
            "en": "Needs cleansing"
          }
        },
        {
          "value": 4,
          "label": {
            "zh": "如影隨形",
            "en": "Lingering shadow"
          }
        }
      ],
      "scoring": {
        "direction": "higher_is_worse",
        "weight": 1.5
      }
    },
    {
      "question_id": "ep_core_3",
      "text": {
        "zh": "您是否常無故感到心頭沉重，事後才發覺那是他人的重擔？",
        "en": "Do you often feel sudden heaviness, only to realize later it was someone else's burden?"
      },
      "type": "core_state",
      "options": [
        {
          "value": 0,
          "label": {
            "zh": "未曾如此",
            "en": "Never"
          }
        },
        {
          "value": 2,
          "label": {
            "zh": "間或有之",
            "en": "Occasionally"
          }
        },
        {
          "value": 4,
          "label": {
            "zh": "習以為常",
            "en": "Habitually"
          }
        }
      ],
      "scoring": {
        "direction": "higher_is_worse",
        "weight": 1.5
      }
    },
    {
      "question_id": "ep_val_1",
      "text": {
        "zh": "親近之人是否形容您如「海綿」一般，總是吸納周遭的氛圍？",
        "en": "Do close ones describe you as a 'sponge', absorbing the surrounding atmosphere?"
      },
      "type": "validation",
      "options": [
        {
          "value": 0,
          "label": {
            "zh": "未曾聽聞",
            "en": "Never heard"
          }
        },
        {
          "value": 2,
          "label": {
            "zh": "偶有此說",
            "en": "Occasionally said"
          }
        },
        {
          "value": 4,
          "label": {
            "zh": "眾人皆知",
            "en": "Widely known"
          }
        }
      ],
      "scoring": {
        "direction": "higher_is_worse",
        "weight": 1.0,
        "exclude_from_volatility": true
      }
    },
    {
      "question_id": "ep_val_2",
      "text": {
        "zh": "在觀看戲劇見人落淚時，您是否比旁人更易隨之氣動神傷？",
        "en": "When seeing tears in dramas, is your spirit more easily moved to sorrow than others?"
      },
      "type": "validation",
      "options": [
        {
          "value": 0,
          "label": {
            "zh": "心如止水",
            "en": "Still water"
          }
        },
        {
          "value": 2,
          "label": {
            "zh": "稍有觸動",
            "en": "Slightly moved"
          }
        },
        {
          "value": 4,
          "label": {
            "zh": "感同身受",
            "en": "Deeply identified"
          }
        }
      ],
      "scoring": {
        "direction": "higher_is_worse",
        "weight": 1.0,
        "exclude_from_volatility": true
      }
    },
    {
      "question_id": "ep_react_1",
      "text": {
        "zh": "當察覺外界紛擾入侵內心時，您的本能反應為何？",
        "en": "When outside chaos invades, what is your instinct?"
      },
      "type": "reaction",
      "options": [
        {
          "value": 0,
          "label": {
            "zh": "收縮邊界",
            "en": "Contract boundary"
          }
        },
        {
          "value": 2,
          "label": {
            "zh": "混亂逃離",
            "en": "Confused flee"
          }
        },
        {
          "value": 4,
          "label": {
            "zh": "隨波逐流",
            "en": "Drift with it"
          }
        }
      ],
      "scoring": {
        "direction": "higher_is_worse",
        "weight": 1.2
      }
    },
    {
      "question_id": "ep_react_2",
      "text": {
        "zh": "若要形容您目前心靈邊界的狀態，何者最貼切？",
        "en": "To describe your spiritual boundary, which fits best?"
      },
      "type": "reaction",
      "options": [
        {
          "value": 0,
          "label": {
            "zh": "厚實城牆",
            "en": "Thick wall"
          }
        },
        {
          "value": 2,
          "label": {
            "zh": "隨風紗簾",
            "en": "Curtain in wind"
          }
        },
        {
          "value": 4,
          "label": {
            "zh": "四面受風",
            "en": "Open to wind"
          }
        }
      ],
      "scoring": {
        "direction": "higher_is_worse",
        "weight": 1.2
      }
    },
    {
      "question_id": "ep_res_1",
      "text": {
        "zh": "您是否擁有某種儀式或處所，能助您洗淨沾染的雜氣？",
        "en": "Do you have a ritual or place to cleanse absorbed impurities?"
      },
      "type": "resource",
      "options": [
        {
          "value": 4,
          "label": {
            "zh": "並無此法",
            "en": "No method"
          }
        },
        {
          "value": 2,
          "label": {
            "zh": "時靈時不靈",
            "en": "Works sometimes"
          }
        },
        {
          "value": 0,
          "label": {
            "zh": "自有妙法",
            "en": "Have method"
          }
        }
      ],
      "scoring": {
        "direction": "higher_is_worse",
        "weight": 1.0,
        "exclude_from_volatility": true
      }
    }
  ]
}